{
    // "posts": [
    //   { "id": 1, "title": "json-server", "author": "typicode" },
    //   { "id": 2, "title": "json-server", "author": "typicode" }
    // ],
    "products": [
        {
            "name":"Hat",
            "img":"",
            "price":"100$"
        },
        {
            "name":"Bag",
            "img":"",
            "price":"140$"
        },
        {
            "name":"Book",
            "img":"",
            "price":"150$"
        }
    ],
    "comments": [
      { "id": 1, "body": "some comment", "postId": 1 }
    ],
    "profile": [{ "name": "typicode" }]
    

  }